discord/__init__.py
discord/calls.py
discord/channel.py
discord/client.py
discord/colour.py
discord/compat.py
discord/embeds.py
discord/emoji.py
discord/enums.py
discord/errors.py
discord/game.py
discord/gateway.py
discord/http.py
discord/invite.py
discord/iterators.py
discord/member.py
discord/message.py
discord/mixins.py
discord/object.py
discord/opus.py
discord/permissions.py
discord/reaction.py
discord/role.py
discord/server.py
discord/state.py
discord/user.py
discord/utils.py
discord/voice_client.py
discord/bin/libopus-0.x64.dll
discord/bin/libopus-0.x86.dll
discord/ext/commands/__init__.py
discord/ext/commands/bot.py
discord/ext/commands/context.py
discord/ext/commands/converter.py
discord/ext/commands/cooldowns.py
discord/ext/commands/core.py
discord/ext/commands/errors.py
discord/ext/commands/formatter.py
discord/ext/commands/view.py
discord-unofficial/__init__.py
discord-unofficial/calls.py
discord-unofficial/channel.py
discord-unofficial/client.py
discord-unofficial/colour.py
discord-unofficial/compat.py
discord-unofficial/embeds.py
discord-unofficial/emoji.py
discord-unofficial/enums.py
discord-unofficial/errors.py
discord-unofficial/game.py
discord-unofficial/gateway.py
discord-unofficial/http.py
discord-unofficial/invite.py
discord-unofficial/iterators.py
discord-unofficial/member.py
discord-unofficial/message.py
discord-unofficial/mixins.py
discord-unofficial/object.py
discord-unofficial/opus.py
discord-unofficial/permissions.py
discord-unofficial/reaction.py
discord-unofficial/role.py
discord-unofficial/server.py
discord-unofficial/state.py
discord-unofficial/user.py
discord-unofficial/utils.py
discord-unofficial/voice_client.py
discord-unofficial/ext/commands/__init__.py
discord-unofficial/ext/commands/bot.py
discord-unofficial/ext/commands/context.py
discord-unofficial/ext/commands/converter.py
discord-unofficial/ext/commands/cooldowns.py
discord-unofficial/ext/commands/core.py
discord-unofficial/ext/commands/errors.py
discord.py_unofficial-0.17.1.dist-info/LICENSE
discord.py_unofficial-0.17.1.dist-info/METADATA
discord.py_unofficial-0.17.1.dist-info/WHEEL
discord.py_unofficial-0.17.1.dist-info/top_level.txt
discord.py_unofficial-0.17.1.dist-info/RECORD
