Metadata-Version: 2.1
Name: discord.py-unofficial
Version: 0.17.1
Summary: A python wrapper for the Discord API
Home-page: https://github.com/RandomGamer123/discord.py-unofficial
Author: RandomGamer123
License: MIT
Platform: UNKNOWN
Classifier: Development Status :: 5 - Production/Stable
Classifier: License :: OSI Approved :: MIT License
Classifier: Intended Audience :: Developers
Classifier: Natural Language :: English
Classifier: Operating System :: OS Independent
Classifier: Programming Language :: Python :: 3.5
Classifier: Programming Language :: Python :: 3.6
Classifier: Programming Language :: Python :: 3.7
Classifier: Topic :: Internet
Classifier: Topic :: Software Development :: Libraries
Classifier: Topic :: Software Development :: Libraries :: Python Modules
Classifier: Topic :: Utilities
Requires-Dist: aiohttp (<3.7,>=3.1)
Requires-Dist: websockets (<7.0,>=6.0)
Provides-Extra: voice
Requires-Dist: PyNaCl (==1.0.1) ; extra == 'voice'
